asyncpgpromise/__init__.py
asyncpgpromise/asyncpgpromise.py
asyncpgpromise-0.1.4.dist-info/METADATA
asyncpgpromise-0.1.4.dist-info/WHEEL
asyncpgpromise-0.1.4.dist-info/top_level.txt
asyncpgpromise-0.1.4.dist-info/RECORD
