Metadata-Version: 2.1
Name: asyncpgpromise
Version: 0.1.4
Summary: pg-promise like wrapper for asyncpg
Home-page: https://github.com/K-NRS/asyncpgpromise
Author: Kerem Noras
Author-email: kerem@noras.tech
Requires-Dist: asyncpg
